odoo/addons/edi_utm_oca/README.rst
odoo/addons/edi_utm_oca/__init__.py
odoo/addons/edi_utm_oca/__manifest__.py
odoo/addons/edi_utm_oca/data/utm_source.xml
odoo/addons/edi_utm_oca/i18n/edi_utm_oca.pot
odoo/addons/edi_utm_oca/i18n/it.po
odoo/addons/edi_utm_oca/models/__init__.py
odoo/addons/edi_utm_oca/models/edi_exchange_consumer_mixin.py
odoo/addons/edi_utm_oca/readme/CONTRIBUTORS.rst
odoo/addons/edi_utm_oca/readme/DESCRIPTION.rst
odoo/addons/edi_utm_oca/static/description/icon.png
odoo/addons/edi_utm_oca/static/description/index.html
odoo/addons/edi_utm_oca/tests/__init__.py
odoo/addons/edi_utm_oca/tests/fake_models.py
odoo/addons/edi_utm_oca/tests/test_edi_utm.py
odoo_addon_edi_utm_oca-16.0.1.0.0.5.dist-info/METADATA
odoo_addon_edi_utm_oca-16.0.1.0.0.5.dist-info/WHEEL
odoo_addon_edi_utm_oca-16.0.1.0.0.5.dist-info/top_level.txt
odoo_addon_edi_utm_oca-16.0.1.0.0.5.dist-info/RECORD
